cursesdict/README.MD
cursesdict/__init__.py
cursesdict/requirements.txt
cursesdict/thirdparty.json
cursesdict-0.13.dist-info/LICENSE.rst
cursesdict-0.13.dist-info/METADATA
cursesdict-0.13.dist-info/WHEEL
cursesdict-0.13.dist-info/top_level.txt
cursesdict-0.13.dist-info/RECORD
