Metadata-Version: 2.1
Name: cursesdict
Version: 0.13
Summary: creates an interactive menu system for your application or program, providing an intuitive and user-friendly interface for users to navigate and perform various actions
Home-page: https://github.com/hansalemaos/cursesdict
Author: Johannes Fischer
Author-email: aulasparticularesdealemaosp@gmail.com
License: MIT
Keywords: curses,menu
Classifier: Development Status :: 4 - Beta
Classifier: Programming Language :: Python :: 3 :: Only
Classifier: Programming Language :: Python :: 3.10
Classifier: Topic :: Software Development :: Libraries :: Python Modules
Classifier: Topic :: Utilities
License-File: LICENSE.rst
Requires-Dist: flatten-everything
